<?xml version="1.0" encoding="utf-8"?>
<TrustFrameworkPolicy xmlns:xsi="http://www.w3.org/2001/XMLSchema-instance" xmlns:xsd="http://www.w3.org/2001/XMLSchema" xmlns="http://schemas.microsoft.com/online/cpim/schemas/2013/06" PolicySchemaVersion="0.3.0.0" 
  TenantId="yourtenant.onmicrosoft.com" 
  PolicyId="B2C_1A_Demo_TrustFrameworkExtensions_FederationForceEmail" 
  PublicPolicyUri="http://yourtenant.onmicrosoft.com/B2C_1A_Demo_TrustFrameworkExtensions_FederationForceEmail">

  <BasePolicy>
    <TenantId>yourtenant.onmicrosoft.com</TenantId>
    <PolicyId>B2C_1A_TrustFrameworkExtensions</PolicyId>
  </BasePolicy>
  <BuildingBlocks></BuildingBlocks>

  <ClaimsProviders>
    <ClaimsProvider>
      <DisplayName>Social accounts</DisplayName>
      <TechnicalProfiles>
        <!-- Collect, validate and return the email address as output claim.
            So, next orchestration step will persist the email to the directory 
            into otherMails attribute -->
        <TechnicalProfile Id="SelfAsserted-SocialEmail">
          <DisplayName>Email signup</DisplayName>
          <Protocol Name="Proprietary" Handler="Web.TPEngine.Providers.SelfAssertedAttributeProvider, Web.TPEngine, Version=1.0.0.0, Culture=neutral, PublicKeyToken=null" />
          <Metadata>
            <Item Key="ContentDefinitionReferenceId">api.localaccountsignup</Item>
            <Item Key="language.button_continue">Continue</Item>
          </Metadata>
          <InputClaims>
            <InputClaim ClaimTypeReferenceId="email" />
          </InputClaims>
          <OutputClaims>
            <OutputClaim ClaimTypeReferenceId="email" PartnerClaimType="Verified.Email" Required="true" />
          </OutputClaims>
          <UseTechnicalProfileForSessionManagement ReferenceId="SM-AAD" />
        </TechnicalProfile>
      </TechnicalProfiles>
    </ClaimsProvider>
  </ClaimsProviders>

  <UserJourneys>

    <UserJourney Id="SignUpOrSignIn_Custom">
      <OrchestrationSteps>

        <OrchestrationStep Order="1" Type="CombinedSignInAndSignUp" ContentDefinitionReferenceId="api.signuporsignin">
          <ClaimsProviderSelections>
            <ClaimsProviderSelection TargetClaimsExchangeId="FacebookExchange" />
            <ClaimsProviderSelection TargetClaimsExchangeId="GoogleExchange" />
            <ClaimsProviderSelection ValidationClaimsExchangeId="LocalAccountSigninEmailExchange" />
          </ClaimsProviderSelections>
          <ClaimsExchanges>
            <ClaimsExchange Id="LocalAccountSigninEmailExchange" TechnicalProfileReferenceId="SelfAsserted-LocalAccountSignin-Email" />
          </ClaimsExchanges>
        </OrchestrationStep>

        <!-- Check if the user has selected to sign in using one of the social providers -->
        <OrchestrationStep Order="2" Type="ClaimsExchange">
          <Preconditions>
            <Precondition Type="ClaimsExist" ExecuteActionsIf="true">
              <Value>objectId</Value>
              <Action>SkipThisOrchestrationStep</Action>
            </Precondition>
          </Preconditions>
          <ClaimsExchanges>
            <ClaimsExchange Id="FacebookExchange" TechnicalProfileReferenceId="Facebook-OAUTH" />
            <ClaimsExchange Id="GoogleExchange" TechnicalProfileReferenceId="Google-OAuth2" />
            <ClaimsExchange Id="SignUpWithLogonEmailExchange" TechnicalProfileReferenceId="LocalAccountSignUpWithLogonEmail" />
          </ClaimsExchanges>
        </OrchestrationStep>

        <!-- For social IDP authentication, attempt to find the user account in the directory. -->
        <OrchestrationStep Order="3" Type="ClaimsExchange">
          <Preconditions>
            <Precondition Type="ClaimEquals" ExecuteActionsIf="true">
              <Value>authenticationSource</Value>
              <Value>localAccountAuthentication</Value>
              <Action>SkipThisOrchestrationStep</Action>
            </Precondition>
          </Preconditions>
          <ClaimsExchanges>
            <ClaimsExchange Id="AADUserReadUsingAlternativeSecurityId" TechnicalProfileReferenceId="AAD-UserReadUsingAlternativeSecurityId-NoError" />
          </ClaimsExchanges>
        </OrchestrationStep>

        <!--Demo: Run this step only if email address is empty and new user.
			The technical profile asks the user to provide and validate the email address.
			The email address return as output claim. So, next step can 
			persist the email to the directory -->
        <OrchestrationStep Order="4" Type="ClaimsExchange">
          <Preconditions>
            <Precondition Type="ClaimsExist" ExecuteActionsIf="true">
              <Value>objectId</Value>
              <Action>SkipThisOrchestrationStep</Action>
            </Precondition>
            <Precondition Type="ClaimsExist" ExecuteActionsIf="true">
              <Value>email</Value>
              <Action>SkipThisOrchestrationStep</Action>
            </Precondition>
          </Preconditions>
          <ClaimsExchanges>
            <ClaimsExchange Id="SelfAsserted-SocialEmail" TechnicalProfileReferenceId="SelfAsserted-SocialEmail" />
          </ClaimsExchanges>
        </OrchestrationStep>

        <!-- Show self-asserted page only if the directory does not have the user account already (i.e. we do not have an objectId). 
          This can only happen when authentication happened using a social IDP. If local account was created or authentication done
          using ESTS in step 2, then an user account must exist in the directory by this time. -->
        <OrchestrationStep Order="5" Type="ClaimsExchange">
          <Preconditions>
            <Precondition Type="ClaimsExist" ExecuteActionsIf="true">
              <Value>objectId</Value>
              <Action>SkipThisOrchestrationStep</Action>
            </Precondition>
          </Preconditions>
          <ClaimsExchanges>
            <ClaimsExchange Id="SelfAsserted-Social" TechnicalProfileReferenceId="SelfAsserted-Social" />
          </ClaimsExchanges>
        </OrchestrationStep>

        <!-- This step reads any user attributes that we may not have received when authenticating using ESTS so they can be sent 
          in the token. -->
        <OrchestrationStep Order="6" Type="ClaimsExchange">
          <Preconditions>
            <Precondition Type="ClaimEquals" ExecuteActionsIf="true">
              <Value>authenticationSource</Value>
              <Value>socialIdpAuthentication</Value>
              <Action>SkipThisOrchestrationStep</Action>
            </Precondition>
          </Preconditions>
          <ClaimsExchanges>
            <ClaimsExchange Id="AADUserReadWithObjectId" TechnicalProfileReferenceId="AAD-UserReadUsingObjectId" />
          </ClaimsExchanges>
        </OrchestrationStep>
        <!-- The previous step (SelfAsserted-Social) could have been skipped if there were no attributes to collect 
             from the user. So, in that case, create the user in the directory if one does not already exist 
             (verified using objectId which would be set from the last step if account was created in the directory. -->
        <OrchestrationStep Order="7" Type="ClaimsExchange">
          <Preconditions>
            <Precondition Type="ClaimsExist" ExecuteActionsIf="true">
              <Value>objectId</Value>
              <Action>SkipThisOrchestrationStep</Action>
            </Precondition>
          </Preconditions>
          <ClaimsExchanges>
            <ClaimsExchange Id="AADUserWrite" TechnicalProfileReferenceId="AAD-UserWriteUsingAlternativeSecurityId" />
          </ClaimsExchanges>
        </OrchestrationStep>

        <OrchestrationStep Order="8" Type="SendClaims" CpimIssuerTechnicalProfileReferenceId="JwtIssuer" />

      </OrchestrationSteps>
      <ClientDefinition ReferenceId="DefaultWeb" />
    </UserJourney>

    <UserJourney Id="ProfileEdit">
      <OrchestrationSteps>

        <OrchestrationStep Order="1" Type="ClaimsProviderSelection" ContentDefinitionReferenceId="api.idpselections">
          <ClaimsProviderSelections>
            <ClaimsProviderSelection TargetClaimsExchangeId="FacebookExchange" />
            <ClaimsProviderSelection TargetClaimsExchangeId="LocalAccountSigninEmailExchange" />
          </ClaimsProviderSelections>
        </OrchestrationStep>
        <OrchestrationStep Order="2" Type="ClaimsExchange">
          <ClaimsExchanges>
            <ClaimsExchange Id="FacebookExchange" TechnicalProfileReferenceId="Facebook-OAUTH" />
            <ClaimsExchange Id="LocalAccountSigninEmailExchange" TechnicalProfileReferenceId="SelfAsserted-LocalAccountSignin-Email" />
          </ClaimsExchanges>
        </OrchestrationStep>
        <OrchestrationStep Order="3" Type="ClaimsExchange">
          <Preconditions>
            <Precondition Type="ClaimEquals" ExecuteActionsIf="true">
              <Value>authenticationSource</Value>
              <Value>localAccountAuthentication</Value>
              <Action>SkipThisOrchestrationStep</Action>
            </Precondition>
          </Preconditions>
          <ClaimsExchanges>
            <ClaimsExchange Id="AADUserRead" TechnicalProfileReferenceId="AAD-UserReadUsingAlternativeSecurityId" />
          </ClaimsExchanges>
        </OrchestrationStep>
        <OrchestrationStep Order="4" Type="ClaimsExchange">
          <Preconditions>
            <Precondition Type="ClaimEquals" ExecuteActionsIf="true">
              <Value>authenticationSource</Value>
              <Value>socialIdpAuthentication</Value>
              <Action>SkipThisOrchestrationStep</Action>
            </Precondition>
          </Preconditions>
          <ClaimsExchanges>
            <ClaimsExchange Id="AADUserReadWithObjectId" TechnicalProfileReferenceId="AAD-UserReadUsingObjectId" />
          </ClaimsExchanges>
        </OrchestrationStep>

        <OrchestrationStep Order="5" Type="ClaimsExchange">
          <ClaimsExchanges>
            <ClaimsExchange Id="B2CUserProfileUpdateExchange" TechnicalProfileReferenceId="SelfAsserted-ProfileUpdate" />
          </ClaimsExchanges>
        </OrchestrationStep>

        <OrchestrationStep Order="6" Type="SendClaims" CpimIssuerTechnicalProfileReferenceId="JwtIssuer" />

      </OrchestrationSteps>
      <ClientDefinition ReferenceId="DefaultWeb" />
    </UserJourney>

    <UserJourney Id="PasswordReset">
      <OrchestrationSteps>
        <OrchestrationStep Order="1" Type="ClaimsExchange">
          <ClaimsExchanges>
            <ClaimsExchange Id="PasswordResetUsingEmailAddressExchange" TechnicalProfileReferenceId="LocalAccountDiscoveryUsingEmailAddress" />
          </ClaimsExchanges>
        </OrchestrationStep>
        <OrchestrationStep Order="2" Type="ClaimsExchange">
          <ClaimsExchanges>
            <ClaimsExchange Id="NewCredentials" TechnicalProfileReferenceId="LocalAccountWritePasswordUsingObjectId" />
          </ClaimsExchanges>
        </OrchestrationStep>
        <OrchestrationStep Order="3" Type="SendClaims" CpimIssuerTechnicalProfileReferenceId="JwtIssuer" />
      </OrchestrationSteps>
      <ClientDefinition ReferenceId="DefaultWeb" />
    </UserJourney>

  </UserJourneys>

</TrustFrameworkPolicy>